setup.py
mollom/__init__.py
mollom/mollom.py
mollom.egg-info/PKG-INFO
mollom.egg-info/SOURCES.txt
mollom.egg-info/dependency_links.txt
mollom.egg-info/requires.txt
mollom.egg-info/top_level.txt