Metadata-Version: 1.0
Name: mollom
Version: 0.1.2
Summary: Mollom client library.
Home-page: https://github.com/Mollom/mollom_python
Author: Huan Lai
Author-email: huan.lai@acquia.com
License: MIT
Platform: UNKNOWN
Classifier: Development Status :: 4 - Beta
Classifier: Intended Audience :: Developers
Classifier: Natural Language :: English
Classifier: License :: OSI Approved :: MIT License
Classifier: Programming Language :: Python :: 2.7
